MANIFEST.in
setup.py
onestop_opensign/__init__.py
onestop_opensign/config.py
onestop_opensign/extension_init.py
onestop_opensign/models.py
onestop_opensign/provider.py
onestop_opensign/urls.py
onestop_opensign/views.py
onestop_opensign.egg-info/PKG-INFO
onestop_opensign.egg-info/SOURCES.txt
onestop_opensign.egg-info/dependency_links.txt
onestop_opensign.egg-info/requires.txt
onestop_opensign.egg-info/top_level.txt
onestop_opensign/fixtures/digital_signature_methods.json
onestop_opensign/migrations/0001_initial.py
onestop_opensign/migrations/__init__.py