Metadata-Version: 2.1
Name: onestop-opensign
Version: 0.1.6.1
Summary: Package for a onestop extension that integrates with the opensign digital signature service.
Author: OTB Africa
Author-email: developers@otbafrica.com
License: BSD 2-clause
Classifier: Programming Language :: Python :: 3
Classifier: License :: OSI Approved :: MIT License
Classifier: Operating System :: OS Independent
Requires-Python: >=3.6
